setup.cfg
setup.py
bin/slackit
slackit/__init__.py
slackit/utils.py
slackit.egg-info/PKG-INFO
slackit.egg-info/SOURCES.txt
slackit.egg-info/dependency_links.txt
slackit.egg-info/requires.txt
slackit.egg-info/top_level.txt