Metadata-Version: 1.0
Name: slackit
Version: 0.1
Summary: Pipe anything to your private Slack channel
Home-page: https://github.com/igniteflow/slackit
Author: Phil Tysoe
Author-email: philtysoe@gmail.com
License: MIT
Platform: UNKNOWN
